[
  {
    "desc": "生成任务",
    "routeId":"",
    "taskName":"",
    "coveringArea":"",
    "executor":0,
    "taskType":0,
    "subId":"",
    "comments":"",
    "taskDes":"",
    "airportId":"",
    "relation_obj":"",
    "taskMode":0,
    "flyModeVal":2,
    "flyMode":"",
    "returnMode":"",
    "flySpeed":null,
    "initSpeed":8,
    "workSpeed":"",
    "routeName":"upload_test_line",
    "totalPoint":5,
    "totalSecond":165,
    "totalDist":107,
    "totalShootPoint":3,
    "offsetDistance":0,
    "aerialDirection":1,
    "routeMissionType":0,
    "cameraMode":1,
    "returnAlt":44,
    "msg": "请求成功",
    "status_code": 200,
    "code": 1
  }
]